multirtc/__init__.py
multirtc/__main__.py
multirtc/base.py
multirtc/create_rtc.py
multirtc/define_geogrid.py
multirtc/dem.py
multirtc/geocode.py
multirtc/multirtc.py
multirtc/rtc_options.py
multirtc/sentinel1.py
multirtc/sicd.py
multirtc/multimetric/ale.py
multirtc/multimetric/corner_reflector.py
multirtc/multimetric/point_target.py
multirtc/multimetric/rle.py
multirtc-0.5.0.dist-info/licenses/LICENSE
multirtc-0.5.0.dist-info/METADATA
multirtc-0.5.0.dist-info/WHEEL
multirtc-0.5.0.dist-info/entry_points.txt
multirtc-0.5.0.dist-info/top_level.txt
multirtc-0.5.0.dist-info/RECORD
