Metadata-Version: 2.4
Name: multirtc
Version: 0.5.0
Summary: Python library for multi-sensor RTC processing using the OPERA algorithm
Author-email: Forrest Williams <ffwilliams2@alaska.edu>
License: BSD-3-Clause
Project-URL: Homepage, https://github.com/forrestfwilliams/multirtc
Project-URL: Documentation, https://github.com/forrestfwilliams/multirtc
Classifier: Intended Audience :: Science/Research
Classifier: License :: OSI Approved :: BSD License
Classifier: Natural Language :: English
Classifier: Operating System :: OS Independent
Classifier: Programming Language :: Python :: 3
Classifier: Programming Language :: Python :: 3.10
Requires-Python: >=3.10
License-File: LICENSE
Requires-Dist: gdal
Requires-Dist: numpy
Requires-Dist: boto3
Requires-Dist: requests
Requires-Dist: lxml
Requires-Dist: shapely
Requires-Dist: pyproj
Requires-Dist: s1reader
Requires-Dist: sarpy
Requires-Dist: burst2safe
Requires-Dist: tqdm
Requires-Dist: hyp3lib
Requires-Dist: matplotlib
Requires-Dist: pandas
Requires-Dist: lmfit
Requires-Dist: scipy
Requires-Dist: scikit-image
Provides-Extra: develop
Requires-Dist: pytest; extra == "develop"
Requires-Dist: pytest-cov; extra == "develop"
Requires-Dist: pytest-console-scripts; extra == "develop"
Requires-Dist: ruff; extra == "develop"
Dynamic: license-file
